py_package/__init__.py
py_package/command_line.py
py_package/module.py
py_package/tests/__init__.py
py_package-0.2.1.dist-info/METADATA
py_package-0.2.1.dist-info/WHEEL
py_package-0.2.1.dist-info/entry_points.txt
py_package-0.2.1.dist-info/top_level.txt
py_package-0.2.1.dist-info/RECORD
