Metadata-Version: 2.1
Name: py-package
Version: 0.2.1
Summary: This is a template repository for creating python packages
Home-page: https://github.com/aahnik/py_package
Author: Aahnik Daw
Author-email: meet.aahnik@gmail.com
License: UNKNOWN
Platform: UNKNOWN
Classifier: Programming Language :: Python :: 3
Classifier: License :: OSI Approved :: MIT License
Classifier: Operating System :: OS Independent
Requires-Python: >=3.6
Requires-Dist: pytest
